src/MyBundle.py
src/__init__.py
src/classes.py
src/functions.py
src/data/__init__.py
src/data/plots/__init__.py
src/data/plots/Demonstration/__init__.py
NCMCM-2.1.dist-info/METADATA
NCMCM-2.1.dist-info/WHEEL
NCMCM-2.1.dist-info/top_level.txt
NCMCM-2.1.dist-info/RECORD
