Metadata-Version: 2.1
Name: NCMCM
Version: 2.1
Summary: A toolbox to visualize neuronal imaging data and apply the NC-MCM framework to it
Home-page: https://github.com/DriftKing1998/NC-MCM-Visualizer
Author: Hofer Michael
Author-email: hofer.michael.98@email.com
Classifier: Programming Language :: Python :: 3
Classifier: License :: OSI Approved :: MIT License
Classifier: Operating System :: OS Independent
Requires-Python: >=3.6
Requires-Dist: numpy
Requires-Dist: matplotlib
Requires-Dist: scikit-learn
Requires-Dist: networkx
Requires-Dist: pyvis
Requires-Dist: statsmodels
Requires-Dist: tensorflow
Requires-Dist: tqdm
Requires-Dist: scipy
